package_kpengz/__init__.py
package_kpengz/constants.py
package_kpengz/functions.py
package_kpengz-1.0.2.dist-info/METADATA
package_kpengz-1.0.2.dist-info/WHEEL
package_kpengz-1.0.2.dist-info/licenses/LICENSE
package_kpengz-1.0.2.dist-info/RECORD
