Metadata-Version: 2.1
Name: package_kpengz
Version: 1.0.2
Summary: Python package for mysql functions
Project-URL: Homepage, https://github.com/pypa/sampleproject
Project-URL: Bug Tracker, https://github.com/pypa/sampleproject/issues
Author-email: Kolitha Perera <kolitha.perera@scania.com>
License-File: LICENSE
Classifier: License :: OSI Approved :: MIT License
Classifier: Operating System :: OS Independent
Classifier: Programming Language :: Python :: 3
Requires-Python: >=3.9
Requires-Dist: mysql-connector-python>=8.0.32
